cv_utils/__init__.py
cv_utils/aruco.py
cv_utils/colmap.py
cv_utils/color.py
cv_utils/core.py
cv_utils/eager_video_capture.py
cv_utils/video.py
cv_utils/video_stream.py
cv_utils/drawing/__init__.py
cv_utils/drawing/matplotlib.py
cv_utils/drawing/opencv.py
wf_cv_utils-3.6.3.dist-info/LICENSE
wf_cv_utils-3.6.3.dist-info/METADATA
wf_cv_utils-3.6.3.dist-info/WHEEL
wf_cv_utils-3.6.3.dist-info/top_level.txt
wf_cv_utils-3.6.3.dist-info/RECORD
