Metadata-Version: 2.1
Name: wf-cv-utils
Version: 3.6.3
Summary: Miscellaneous utilities for working with camera data
Home-page: https://github.com/WildflowerSchools/wf-cv-utils
Author: Theodore Quinn
Author-email: ted.quinn@wildflowerschools.org
License: UNKNOWN
Keywords: cv
Platform: UNKNOWN
Classifier: Intended Audience :: Developers
Classifier: License :: OSI Approved :: MIT License
Classifier: Operating System :: OS Independent
Classifier: Programming Language :: Python
License-File: LICENSE
Requires-Dist: opencv-python (>=4.5.1)
Requires-Dist: pandas (>=1.2.2)
Requires-Dist: numpy (>=1.20.1)
Requires-Dist: matplotlib (>=3.3.4)
